crashbang/__init__.py
crashbang/command.py
crashbang/helper.py
Crashbang-0.0.2.dist-info/LICENSE
Crashbang-0.0.2.dist-info/METADATA
Crashbang-0.0.2.dist-info/WHEEL
Crashbang-0.0.2.dist-info/entry_points.txt
Crashbang-0.0.2.dist-info/top_level.txt
Crashbang-0.0.2.dist-info/RECORD
