Metadata-Version: 2.1
Name: Crashbang
Version: 0.0.2
Summary: A tool to aid in testing the stability of programs
Author-email: Ian Santopietro <isantop@gmail.com>
Project-URL: Homepage, https://github.com/isantop/crashbang
Project-URL: Bug Tracker, https://github.com/isantop/crashbang/issues
Classifier: Programming Language :: Python :: 3
Classifier: License :: OSI Approved :: Mozilla Public License 2.0 (MPL 2.0)
Classifier: Operating System :: POSIX :: Linux
Classifier: Development Status :: 3 - Alpha
Classifier: Environment :: Console
Classifier: Intended Audience :: Developers
Classifier: Intended Audience :: Information Technology
Classifier: Intended Audience :: System Administrators
Classifier: Topic :: Software Development
Requires-Python: >=3.8
License-File: LICENSE
